<?xml version="1.0" encoding="UTF-8"?>
<!DOCTYPE filesystem PUBLIC "-//NetBeans//DTD Filesystem 1.2//EN" "http://www.netbeans.org/dtds/filesystem-1_2.dtd">
<filesystem>

<folder name="Editors">
        <folder name="text">
            <folder name="x-kt">
                <attr name="SystemFileSystem.localizingBundle" stringvalue="org.black.kotlin.Bundle"/>
                <folder name="FontsColors">
                    <folder name="NetBeans">
                        <folder name="Defaults">
                            <file name="FontAndColors.xml" url="FontAndColors.xml">
                                <attr name="SystemFileSystem.localizingBundle" stringvalue="org.black.kotlin.Bundle"/>
                            </file>
                        </folder>
                    </folder>
                </folder>
                
                <file name="JavaIndexer.shadow">
                    <attr name="originalFile" stringvalue="Editors/text/x-java/JavaIndexer.instance"/>
                </file>
            </folder>
        </folder>
</folder>

    <folder name="OptionsDialog">
        <folder name="PreviewExamples">
            <folder name="text">
                <file name="x-kt" url="KtTemplate.kt"/>
            </folder>
        </folder>
    </folder>


    <folder name="Templates">
        <folder name="Kotlin">
            <file name="Kotlin.kt" url="Kotlin file">
                <attr name="SystemFileSystem.localizingBundle" stringvalue="org.black.kotlin.Bundle"/>
                <attr name="template" boolvalue="true"/>
            </file>
        </folder>
    </folder>

</filesystem>
